camfitool/__init__.py
camfitool/camfitool_main.py
camfitool/class_fi_offline_ui.py
camfitool/class_fi_realtime_ui.py
camfitool/icons_rc.py
camfitool/offline_fault_injector_ui.py
camfitool/realtime_fault_injector_ui.py
camfitool/ui_interface.py
camfitool-1.2.3.20.dist-info/LICENCE
camfitool-1.2.3.20.dist-info/METADATA
camfitool-1.2.3.20.dist-info/WHEEL
camfitool-1.2.3.20.dist-info/top_level.txt
camfitool-1.2.3.20.dist-info/RECORD
