Metadata-Version: 2.1
Name: camfitool
Version: 1.2.3.20
Summary: Simple interface that allows injection of image faults into robot cameras.
Home-page: UNKNOWN
Author: Alim Kerem Erdogmus (Inovasyon Muhendislik)
Author-email: <kerem.erdogmus@inovasyonmuhendislik.com>
License: Apache Software License
Project-URL: Inovasyon Muhendislik, https://www.inorobotics.com/
Project-URL: Github Wiki, https://github.com/inomuh/camfitool/wiki
Project-URL: ROS Wiki, http://wiki.ros.org/camfitool/
Project-URL: Download, https://github.com/inomuh/camfitool/releases
Project-URL: Github Repository, https://github.com/inomuh/camfitool
Keywords: python3,ros noetic,fault injection,image database,image faults,robot cameras
Platform: UNKNOWN
Classifier: Development Status :: 3 - Alpha
Classifier: Intended Audience :: Developers
Classifier: Programming Language :: Python :: 3
Classifier: Operating System :: Unix
Classifier: Operating System :: Microsoft :: Windows
License-File: LICENCE
Requires-Dist: opencv-python
Requires-Dist: PyQt5
Requires-Dist: Pillow
